{"indicators":[{"id":"SPX","name":"S&P 500","value":6908.86,"change":-37.27,"unit":"Index","updated":"02/26/26 EST","source":"CNBC"},{"id":"IXIC","name":"Nasdaq","value":22878.383,"change":-273.694,"unit":"Index","updated":"02/26/26 EST","source":"CNBC"},{"id":"DXY","name":"DXY (US Dollar)","value":97.649,"change":-0.142,"unit":"Index","updated":"12:00 AM EST","source":"CNBC"},{"id":"US10Y","name":"US 10Y Treasury","value":3.994,"change":-0.023,"unit":"%","updated":"11:59 PM EST","source":"CNBC"},{"id":"US2Y","name":"US 2Y Treasury","value":3.416,"change":-0.032,"unit":"%","updated":"11:54 PM EST","source":"CNBC"},{"id":"VIX","name":"VIX","value":18.63,"change":0.7,"unit":"Index","updated":"02/26/26 EST","source":"CNBC"},{"id":"GOLD","name":"Gold","value":5201.9,"change":7.7,"unit":"USD","updated":"02/26/26 EST","source":"CNBC"},{"id":"DFF","name":"Fed Funds Rate","value":3.64,"change":0.0,"unit":"%","updated":"2026-02-25","source":"FRED"}],"generated":"2026-02-27T05:00:28.629371+00:00"}